usps_lib/__init__.py
usps_lib/address_validate_request.py
usps_lib/address_validate_response.py
usps_lib/carrier_pickup_availability_request.py
usps_lib/carrier_pickup_availability_response.py
usps_lib/carrier_pickup_cancel_request.py
usps_lib/carrier_pickup_cancel_response.py
usps_lib/carrier_pickup_change_request.py
usps_lib/carrier_pickup_change_response.py
usps_lib/carrier_pickup_inquiry_request.py
usps_lib/carrier_pickup_inquiry_response.py
usps_lib/carrier_pickup_schedule_request.py
usps_lib/carrier_pickup_schedule_response.py
usps_lib/city_state_lookup_request.py
usps_lib/city_state_lookup_response.py
usps_lib/emrsv4_0_bulk_request.py
usps_lib/error.py
usps_lib/evs_cancel_request.py
usps_lib/evs_cancel_response.py
usps_lib/evs_express_mail_intl_request.py
usps_lib/evs_express_mail_intl_response.py
usps_lib/evs_first_class_mail_intl_request.py
usps_lib/evs_first_class_mail_intl_response.py
usps_lib/evs_gxg_get_label_request.py
usps_lib/evs_gxg_get_label_response.py
usps_lib/evs_priority_mail_intl_request.py
usps_lib/evs_priority_mail_intl_response.py
usps_lib/evs_request.py
usps_lib/evs_response.py
usps_lib/evsi_cancel_request.py
usps_lib/evsi_cancel_response.py
usps_lib/express_mail_commitment_request.py
usps_lib/express_mail_commitment_response.py
usps_lib/first_class_mail_request.py
usps_lib/first_class_mail_response.py
usps_lib/hfp_facility_info_request.py
usps_lib/hfp_facility_info_response.py
usps_lib/intl_rate_v2_request.py
usps_lib/intl_rate_v2_response.py
usps_lib/mrsv4_0_request.py
usps_lib/priority_mail_request.py
usps_lib/priority_mail_response.py
usps_lib/pts_email_request.py
usps_lib/pts_emailresult.py
usps_lib/ptspod_request.py
usps_lib/ptspod_result.py
usps_lib/ptsrre_request.py
usps_lib/ptsrre_result.py
usps_lib/ptstpod_request.py
usps_lib/ptstpod_result.py
usps_lib/rate_v4_request.py
usps_lib/rate_v4_response.py
usps_lib/scan_request.py
usps_lib/scan_response.py
usps_lib/sdc_get_locations_request.py
usps_lib/sdc_get_locations_response.py
carrier.usps-2022.6.dist-info/WHEEL
carrier.usps-2022.6.dist-info/METADATA
carrier.usps-2022.6.dist-info/RECORD
